bqrun/__init__.py
bqrun/bqrun.py
bqrun/cli.py
bqrun-3.0.0.dist-info/LICENSE
bqrun-3.0.0.dist-info/METADATA
bqrun-3.0.0.dist-info/WHEEL
bqrun-3.0.0.dist-info/entry_points.txt
bqrun-3.0.0.dist-info/RECORD
