Metadata-Version: 2.1
Name: bqrun
Version: 3.0.0
Summary: Query runner for BigQuery. It automatically analyzes dependencies and runs only necessary queries in parallel.
Home-page: https://github.com/hotoku/bqrun
License: MIT
Keywords: bigquery
Author: Yasunori Horikoshi
Author-email: horikoshi.et.al@gmail.com
Requires-Python: >=3.7,<4.0
Classifier: License :: OSI Approved :: MIT License
Classifier: Programming Language :: Python :: 3
Classifier: Programming Language :: Python :: 3.7
Classifier: Programming Language :: Python :: 3.8
Classifier: Programming Language :: Python :: 3.9
Classifier: Programming Language :: Python :: 3.10
Classifier: Programming Language :: Python :: 3.11
Requires-Dist: Jinja2 (>=3.0.3,<4.0.0)
Requires-Dist: networkx (>=2.6.3,<3.0.0)
Requires-Dist: pydot (>=1.4.2,<2.0.0)
Requires-Dist: wheel (>=0.42.0,<0.43.0)
Project-URL: Repository, https://github.com/hotoku/bqrun
